enhanced_coreapi_client/__init__.py
enhanced_coreapi_client/models.py
enhanced_coreapi_client-1.3.0.dist-info/METADATA
enhanced_coreapi_client-1.3.0.dist-info/WHEEL
enhanced_coreapi_client-1.3.0.dist-info/top_level.txt
enhanced_coreapi_client-1.3.0.dist-info/zip-safe
enhanced_coreapi_client-1.3.0.dist-info/RECORD
