Metadata-Version: 2.1
Name: enhanced-coreapi-client
Version: 1.3.0
Summary: Enhanced CoreAPI client
Home-page: https://gitlab.com/murchik/enhanced-coreapi-client
Author: murchik
Author-email: murchik@protonmail.com
License: GNU General Public License v3 (GPLv3)
Keywords: enhanced-coreapi-client
Platform: UNKNOWN
Classifier: Development Status :: 3 - Alpha
Classifier: Intended Audience :: Developers
Classifier: Operating System :: OS Independent
Classifier: Natural Language :: English
Classifier: Programming Language :: Python :: 2
Classifier: Programming Language :: Python :: 2.7
Classifier: Programming Language :: Python :: 3
Classifier: Programming Language :: Python :: 3.4
Classifier: Programming Language :: Python :: 3.5
Classifier: Programming Language :: Python :: 3.6
Classifier: Programming Language :: Python :: 3.7
Classifier: Programming Language :: Python :: 3.8
Classifier: Programming Language :: Python :: 3.9
Requires-Dist: coreapi (>=2.3)
Provides-Extra: dev
Requires-Dist: ipython ; extra == 'dev'
